[
  {
    "id": 1,
    "name": "Dirt Bike Outlet",
    "address": "123 Main St",
    "city": "Anytown",
    "state": "CA",
    "zip": "90210",
    "phone": "(555) 123-4567",
    "email": "sales@dirtbikeoutlet.com",
    "logo": "company1.png"
  },
  {
    "id": 2,
    "name": "MotoSport",
    "address": "456 Oak St",
    "city": "Somewhere",
    "state": "NV",
    "zip": "89109",
    "phone": "(555) 987-6543",
    "email": "info@motosport.com",
    "logo": "company2.png"
  },
  {
    "id": 3,
    "name": "Cycle Gear",
    "address": "789 Maple Ave",
    "city": "Nowhere",
    "state": "FL",
    "zip": "33000",
    "phone": "(555) 555-5555",
    "email": "customerservice@cyclegear.com",
    "logo": "company3.png"
  },
  {
    "id": 4,
    "name": "Fixies Engine",
    "address": "789 Bronx",
    "city": "Manhattan",
    "state": "NY",
    "zip": "33000",
    "phone": "(555) 456-8536",
    "email": "clienthelp@fixies.com",
    "logo": "company4.png"
  }
]
  